{
  "id": "g8s2-ch5-02",
  "topicId": "math-8-2-05",
  "question": "민수는 학교 축제에서 주사위 두 개를 동시에 던지는 게임에 참여했습니다. 이 게임에서 두 주사위 눈의 합이 소수(1과 자기 자신만으로 나누어떨어지는 1보다 큰 양의 정수)가 나오면 상품을 받을 수 있습니다. 민수가 상품을 받을 확률을 구하세요.",
  "difficulty": 2,
  "hints": [
    "힌트 1: 주사위 두 개를 던질 때 나타날 수 있는 모든 경우의 수를 먼저 구해보세요.",
    "힌트 2: 두 눈의 합이 될 수 있는 범위 내에서 소수(2, 3, 5, 7, 11 등)를 모두 찾아보세요.",
    "힌트 3: 각 소수가 나올 수 있는 경우의 수를 모두 더한 뒤, 전체 경우의 수로 나누어 약분하세요."
  ],
  "choices": [
    "$\\frac{1}{6}$",
    "$\\frac{1}{4}$",
    "$\\frac{5}{12}$",
    "$\\frac{7}{12}$",
    "$\\frac{5}{6}$"
  ],
  "solution": "1. **전체 경우의 수 구하기**\n주사위 두 개를 던질 때 일어날 수 있는 모든 경우의 수는 $6 \\times 6 = 36$가지입니다.\n\n2. **사건의 경우의 수(두 눈의 합이 소수인 경우) 구하기**\n두 눈의 합이 될 수 있는 가장 작은 수는 $1+1=2$이고, 가장 큰 수는 $6+6=12$입니다. 이 범위($2$부터 $12$까지)에 있는 소수는 $2, 3, 5, 7, 11$입니다. 각 합이 나오는 경우를 찾아봅시다.\n- 합이 $2$인 경우: $(1, 1)$ $\\rightarrow$ $1$가지\n- 합이 $3$인 경우: $(1, 2), (2, 1)$ $\\rightarrow$ $2$가지\n- 합이 $5$인 경우: $(1, 4), (2, 3), (3, 2), (4, 1)$ $\\rightarrow$ $4$가지\n- 합이 $7$인 경우: $(1, 6), (2, 5), (3, 4), (4, 3), (5, 2), (6, 1)$ $\\rightarrow$ $6$가지\n- 합이 $11$인 경우: $(5, 6), (6, 5)$ $\\rightarrow$ $2$가지\n\n따라서 합이 소수인 경우의 수는 모두 $1 + 2 + 4 + 6 + 2 = 15$가지입니다.\n\n3. **확률 계산하기**\n$\\text{확률} = \\frac{\\text{사건의 경우의 수}}{\\text{전체 경우의 수}} = \\frac{15}{36}$\n이 분수를 $3$으로 약분하면 $\\frac{5}{12}$가 됩니다.",
  "answer": "$\\frac{5}{12}$",
  "concepts": [
    "경우의 수",
    "확률의 계산",
    "소수"
  ]
}